arithmetic_dice_roller/__init__.py
arithmetic_dice_roller/__main__.py
arithmetic_dice_roller/roller.py
arithmetic_dice_roller-0.3.3.dist-info/METADATA
arithmetic_dice_roller-0.3.3.dist-info/WHEEL
arithmetic_dice_roller-0.3.3.dist-info/entry_points.txt
arithmetic_dice_roller-0.3.3.dist-info/top_level.txt
arithmetic_dice_roller-0.3.3.dist-info/RECORD
