Metadata-Version: 2.1
Name: arithmetic-dice-roller
Version: 0.3.3
Summary: A handy dice roller with extended notation and arithmetic expressions management.
Home-page: https://github.com/massimopavoni/arithmetic-dice-roller
Author: Massimo Pavoni
Author-email: maspavoni@gmail.com
Platform: OS Independent
Classifier: License :: OSI Approved :: GNU General Public License v3 (GPLv3)
Classifier: Programming Language :: Python
Classifier: Operating System :: OS Independent
Requires-Python: >=3.11
Requires-Dist: sympy >=1.12
